mixpeek/__init__.py
mixpeek-1.7.dist-info/LICENSE.rst
mixpeek-1.7.dist-info/METADATA
mixpeek-1.7.dist-info/WHEEL
mixpeek-1.7.dist-info/top_level.txt
mixpeek-1.7.dist-info/RECORD
