Metadata-Version: 2.1
Name: mixpeek
Version: 1.7
Summary: full-text file search API
Home-page: https://github.com/mixpeek/mixpeek-python
Author: Ethan Steininger
Author-email: info@mixpeek.com
License: MIT
Keywords: file search
License-File: LICENSE.rst
Requires-Dist: requests
